<page xmlns:xsi="http://www.w3.org/2001/XMLSchema-instance" layout="admin-1column" xsi:noNamespaceSchemaLocation="urn:magento:framework:View/Layout/etc/page_configuration.xsd" label="Customer My Account (All Pages)" design_abstraction="custom">
    <head>
        <title>Database examples</title>
    </head>
    <body>
        <referenceContainer name="content">
            <block name="version.retrieval" template="Chapter3_Staging::example1.phtml">
                <arguments>
                    <argument name="choose_staging_update" xsi:type="object">Chapter3\Staging\ViewModel\ChooseStagingUpdate</argument>
                    <argument name="current_product" xsi:type="object">Chapter3\Staging\ViewModel\CurrentProduct</argument>
                </arguments>
            </block>
        </referenceContainer>
    </body>
</page>